[
  {
    "_id": "mny75hjnonqbjx",
    "rollNo": "1001",
    "studentName": "Ahmed Raza Khan",
    "class": "10 (Matric)",
    "section": "A",
    "exam": "Annual 2025",
    "year": "2025",
    "remarks": "Excellent performance. Keep it up!",
    "subjects": [
      {
        "name": "Urdu",
        "totalMarks": 100,
        "obtainedMarks": 88
      },
      {
        "name": "English",
        "totalMarks": 100,
        "obtainedMarks": 82
      },
      {
        "name": "Mathematics",
        "totalMarks": 100,
        "obtainedMarks": 91
      },
      {
        "name": "Physics",
        "totalMarks": 100,
        "obtainedMarks": 85
      },
      {
        "name": "Chemistry",
        "totalMarks": 100,
        "obtainedMarks": 78
      },
      {
        "name": "Islamiyat",
        "totalMarks": 50,
        "obtainedMarks": 44
      },
      {
        "name": "Pak Studies",
        "totalMarks": 50,
        "obtainedMarks": 41
      }
    ],
    "createdAt": "2026-04-14T05:44:27.155Z"
  },
  {
    "_id": "mny75hjnrupg7b",
    "rollNo": "1002",
    "studentName": "Sara Bibi",
    "class": "10 (Matric)",
    "section": "A",
    "exam": "Annual 2025",
    "year": "2025",
    "remarks": "Good work. Focus more on Mathematics.",
    "subjects": [
      {
        "name": "Urdu",
        "totalMarks": 100,
        "obtainedMarks": 79
      },
      {
        "name": "English",
        "totalMarks": 100,
        "obtainedMarks": 85
      },
      {
        "name": "Mathematics",
        "totalMarks": 100,
        "obtainedMarks": 61
      },
      {
        "name": "Physics",
        "totalMarks": 100,
        "obtainedMarks": 70
      },
      {
        "name": "Chemistry",
        "totalMarks": 100,
        "obtainedMarks": 68
      },
      {
        "name": "Islamiyat",
        "totalMarks": 50,
        "obtainedMarks": 43
      },
      {
        "name": "Pak Studies",
        "totalMarks": 50,
        "obtainedMarks": 38
      }
    ],
    "createdAt": "2026-04-14T05:44:27.156Z"
  },
  {
    "_id": "mny75hjojz8ubl",
    "rollNo": "1003",
    "studentName": "Usman Tariq",
    "class": "9",
    "section": "B",
    "exam": "Annual 2025",
    "year": "2025",
    "remarks": "Satisfactory. Needs improvement in Science.",
    "subjects": [
      {
        "name": "Urdu",
        "totalMarks": 100,
        "obtainedMarks": 65
      },
      {
        "name": "English",
        "totalMarks": 100,
        "obtainedMarks": 58
      },
      {
        "name": "Mathematics",
        "totalMarks": 100,
        "obtainedMarks": 72
      },
      {
        "name": "Biology",
        "totalMarks": 100,
        "obtainedMarks": 54
      },
      {
        "name": "Islamiyat",
        "totalMarks": 50,
        "obtainedMarks": 35
      },
      {
        "name": "Pak Studies",
        "totalMarks": 50,
        "obtainedMarks": 32
      }
    ],
    "createdAt": "2026-04-14T05:44:27.156Z"
  }
]